{ 
    "_id" : ObjectId("5b7a85856ba55a001459e76c"), 
    "congregation" : ObjectId("59ad334be52d8108cc2ca573"), 
    "date" : ISODate("2018-09-19T10:00:00.000+0000"), 
    "completed" : false, 
    "type" : {
        "withSupervisor" : true, 
        "disableSchool" : false, 
        "meeting" : true, 
        "label" : "Adunanza normale", 
        "id" : NumberInt(0)
    }, 
    "supervisor" : false, 
    "primarySchool" : true, 
    "secondarySchool" : true, 
    "initialPrayer" : null, 
    "finalPrayer" : null, 
    "president" : null, 
    "initialSong" : "  <a href=\"/it/wol/pc/r6/lp-i/202018327/0/0\">Cantico 2</a> e preghiera", 
    "finalSong" : "  <a target=\"_blank\" href=\"https://wol.jw.org/it/wol/pc/r6/lp-i/202018327/12/0\">Cantico&#xA0;89</a> e preghiera", 
    "intervalSong" : "  <a target=\"_blank\" href=\"https://wol.jw.org/it/wol/pc/r6/lp-i/202018327/9/0\">Cantico&#xA0;31</a>", 
    "congregationBibleStudy" : {
        "brother" : null, 
        "label" : "  <strong>Studio biblico di congregazione: </strong>(30&#xA0;min) <a target=\"_blank\" href=\"https://wol.jw.org/it/wol/pc/r6/lp-i/202018327/11/0\"><em>jy </em>cap.&#xA0;35 parr.&#xA0;28-36</a>", 
        "reader" : null
    }, 
    "christianLivingPart" : [
        {
            "label" : "  <strong>Com&#x2019;&#xE8; andata?: </strong>(5&#xA0;min) Trattazione. Incoraggia i presenti a raccontare le esperienze che hanno avuto iniziando conversazioni che hanno permesso di dare testimonianza.", 
            "brother" : ObjectId("594bdb253545c51678fbad0a"), 
            "_id" : ObjectId("5b7a85856ba55a001459e76e")
        }, 
        {
            "label" : "  <strong>&#x201C;</strong><a target=\"_blank\" href=\"https://wol.jw.org/it/wol/pc/r6/lp-i/202018327/10/0\"><strong>Non si sprec&#xF2; nulla</strong></a><strong>&#x201D;: </strong>(10&#xA0;min) Trattazione. Fai vedere l&#x2019;estratto del video <a target=\"_blank\" href=\"http://www.jw.org/finder?pub=mwbv&amp;issue=201809&amp;track=8\" data-video=\"webpubvid://?pub=mwbv&amp;issue=201809&amp;track=8\"><em>Progetti ecosostenibili che recano onore a Geova</em></a>.", 
            "brother" : ObjectId("594bdb773545c51678fbad0d"), 
            "_id" : ObjectId("5b7a85856ba55a001459e76d")
        }
    ], 
    "bibleStudy" : {
        "label" : "  <strong>Video della seconda visita ulteriore: </strong>(5&#xA0;min) Mostra il <a target=\"_blank\" href=\"http://www.jw.org/finder?pub=mwbv&amp;issue=201809&amp;track=3\" data-video=\"webpubvid://?pub=mwbv&amp;issue=201809&amp;track=3\">video</a> e trattalo con l&#x2019;uditorio.", 
        "video" : true, 
        "secondarySchool" : {
            "gender" : "", 
            "student" : null, 
            "assistant" : null, 
            "updated" : false, 
            "made" : NumberInt(0), 
            "pointCompleted" : false
        }, 
        "primarySchool" : {
            "gender" : "", 
            "student" : null, 
            "assistant" : null, 
            "updated" : false, 
            "made" : NumberInt(0), 
            "pointCompleted" : false
        }
    }, 
    "returnVisit" : {
        "label" : "  <strong>Prima visita ulteriore: </strong>(3&#xA0;min o meno) Inizia con la <a target=\"_blank\" class=\"it\" href=\"https://wol.jw.org/it/wol/tc/r6/lp-i/202018327/1\">conversazione modello</a>. La persona ti dice che &#xE8; cristiana.", 
        "video" : false, 
        "secondarySchool" : {
            "gender" : "", 
            "student" : null, 
            "assistant" : null, 
            "updated" : false, 
            "made" : NumberInt(0), 
            "pointCompleted" : false
        }, 
        "primarySchool" : {
            "gender" : "", 
            "student" : null, 
            "assistant" : null, 
            "updated" : false, 
            "made" : NumberInt(0), 
            "pointCompleted" : false
        }
    }, 
    "initialCall" : {
        "label" : "  <strong>Primo contatto: </strong>(2&#xA0;min o meno) Inizia con la <a target=\"_blank\" class=\"it\" href=\"https://wol.jw.org/it/wol/tc/r6/lp-i/202018327/0\">conversazione modello</a>. La persona solleva un&#x2019;obiezione comune nel territorio.", 
        "video" : false, 
        "secondarySchool" : {
            "gender" : "", 
            "student" : null, 
            "assistant" : null, 
            "updated" : false, 
            "made" : NumberInt(0), 
            "pointCompleted" : false
        }, 
        "primarySchool" : {
            "gender" : "", 
            "student" : null, 
            "assistant" : null, 
            "updated" : false, 
            "made" : NumberInt(0), 
            "pointCompleted" : false
        }
    }, 
    "bibleReading" : {
        "label" : "  <strong>Lettura biblica: </strong>(4&#xA0;min o meno) <a target=\"_blank\" href=\"https://wol.jw.org/it/wol/bc/r6/lp-i/202018327/6/0\" data-bid=\"7-1\" class=\"b\">Gv 6:41-59</a>", 
        "secondarySchool" : {
            "student" : null, 
            "updated" : false, 
            "made" : NumberInt(0), 
            "pointCompleted" : false
        }, 
        "primarySchool" : {
            "student" : null, 
            "updated" : false, 
            "made" : NumberInt(0), 
            "pointCompleted" : false
        }
    }, 
    "presentationExercise" : {
        "enabled" : false, 
        "brother" : null, 
        "label" : ""
    }, 
    "gems" : {
        "brother" : null, 
        "label" : "  <strong>Scaviamo per trovare gemme spirituali: </strong>(8&#xA0;min)"
    }, 
    "talk" : {
        "brother" : null, 
        "label" : "  <strong>&#x201C;</strong><a target=\"_blank\" href=\"https://wol.jw.org/it/wol/pc/r6/lp-i/202018327/1/0\"><strong>Seguiamo Ges&#xF9; con i giusti motivi</strong></a><strong>&#x201D;: </strong>(10&#xA0;min)"
    }, 
    "__v" : NumberInt(0)
}
{ 
    "_id" : ObjectId("5b7a85856ba55a001459e767"), 
    "congregation" : ObjectId("59ad334be52d8108cc2ca573"), 
    "date" : ISODate("2018-09-05T10:00:00.000+0000"), 
    "completed" : false, 
    "type" : {
        "withSupervisor" : true, 
        "disableSchool" : false, 
        "meeting" : true, 
        "label" : "Adunanza normale", 
        "id" : NumberInt(0)
    }, 
    "supervisor" : false, 
    "primarySchool" : true, 
    "secondarySchool" : true, 
    "initialPrayer" : null, 
    "finalPrayer" : null, 
    "president" : null, 
    "initialSong" : "  <a href=\"/it/wol/pc/r6/lp-i/202018322/0/0\">Cantico&#xA0;13</a> e preghiera", 
    "finalSong" : "  <a target=\"_blank\" href=\"https://wol.jw.org/it/wol/pc/r6/lp-i/202018322/10/0\">Cantico 121</a> e preghiera", 
    "intervalSong" : "  <a target=\"_blank\" href=\"https://wol.jw.org/it/wol/pc/r6/lp-i/202018322/8/0\">Cantico&#xA0;38</a>", 
    "congregationBibleStudy" : {
        "brother" : null, 
        "label" : "  <strong>Studio biblico di congregazione: </strong>(30&#xA0;min) <a target=\"_blank\" href=\"https://wol.jw.org/it/wol/pc/r6/lp-i/202018322/9/0\"><em>jy </em>cap.&#xA0;35 parr.&#xA0;12-19</a>", 
        "reader" : null
    }, 
    "christianLivingPart" : [
        {
            "label" : "  <strong>Bisogni locali: </strong>(8&#xA0;min)", 
            "brother" : ObjectId("594bdbcc3545c51678fbad0e"), 
            "_id" : ObjectId("5b7a85856ba55a001459e769")
        }, 
        {
            "label" : "  <strong>Risultati raggiunti dall&#x2019;organizzazione: </strong>(7&#xA0;min) Fai vedere il video <a target=\"_blank\" href=\"http://www.jw.org/finder?pub=mwbv&amp;issue=201809&amp;track=4\" data-video=\"webpubvid://?pub=mwbv&amp;issue=201809&amp;track=4\"><em>Risultati raggiunti dall&#x2019;organizzazione</em></a> di settembre.", 
            "brother" : null, 
            "president" : true, 
            "_id" : ObjectId("5b7a85856ba55a001459e768")
        }
    ], 
    "bibleStudy" : {
        "label" : "  <strong>Studio biblico: </strong>(6&#xA0;min o meno) <a target=\"_blank\" href=\"https://wol.jw.org/it/wol/pc/r6/lp-i/202018322/7/0\"><em>bhs </em>50, verit&#xE0;&#xA0;2</a>", 
        "video" : false, 
        "secondarySchool" : {
            "gender" : "", 
            "student" : null, 
            "isTalk" : false, 
            "assistant" : null, 
            "updated" : false, 
            "made" : NumberInt(0), 
            "pointCompleted" : false
        }, 
        "primarySchool" : {
            "gender" : "", 
            "student" : null, 
            "isTalk" : false, 
            "assistant" : null, 
            "updated" : false, 
            "made" : NumberInt(0), 
            "pointCompleted" : false
        }
    }, 
    "returnVisit" : {
        "label" : "  <strong>Prima visita ulteriore: </strong>(3&#xA0;min o meno) Usa la <a target=\"_blank\" class=\"it\" href=\"https://wol.jw.org/it/wol/tc/r6/lp-i/202018322/0\">conversazione modello</a>.", 
        "video" : false, 
        "secondarySchool" : {
            "gender" : "", 
            "student" : null, 
            "assistant" : null, 
            "updated" : false, 
            "made" : NumberInt(0), 
            "pointCompleted" : false
        }, 
        "primarySchool" : {
            "gender" : "", 
            "student" : null, 
            "assistant" : null, 
            "updated" : false, 
            "made" : NumberInt(0), 
            "pointCompleted" : false
        }
    }, 
    "initialCall" : {
        "label" : "  <strong>Video del primo contatto: </strong>(4&#xA0;min) Fai vedere il <a target=\"_blank\" href=\"http://www.jw.org/finder?pub=mwbv&amp;issue=201809&amp;track=1\" data-video=\"webpubvid://?pub=mwbv&amp;issue=201809&amp;track=1\">video</a> e trattalo con l&#x2019;uditorio.", 
        "video" : true, 
        "secondarySchool" : {
            "gender" : "", 
            "student" : null, 
            "assistant" : null, 
            "updated" : false, 
            "made" : NumberInt(0), 
            "pointCompleted" : false
        }, 
        "primarySchool" : {
            "gender" : "", 
            "student" : null, 
            "assistant" : null, 
            "updated" : false, 
            "made" : NumberInt(0), 
            "pointCompleted" : false
        }
    }, 
    "bibleReading" : {
        "label" : "  <strong>Lettura biblica: </strong>(4&#xA0;min o meno) <a target=\"_blank\" href=\"https://wol.jw.org/it/wol/bc/r6/lp-i/202018322/5/0\" data-bid=\"6-1\" class=\"b\">Gv 1:1-18</a>", 
        "secondarySchool" : {
            "student" : null, 
            "updated" : false, 
            "made" : NumberInt(0), 
            "pointCompleted" : false
        }, 
        "primarySchool" : {
            "student" : null, 
            "updated" : false, 
            "made" : NumberInt(0), 
            "pointCompleted" : false
        }
    }, 
    "presentationExercise" : {
        "enabled" : false, 
        "brother" : null, 
        "label" : ""
    }, 
    "gems" : {
        "brother" : null, 
        "label" : "  <strong>Scaviamo per trovare gemme spirituali: </strong>(8&#xA0;min)"
    }, 
    "talk" : {
        "brother" : null, 
        "label" : "  <strong>&#x201C;</strong><a target=\"_blank\" href=\"https://wol.jw.org/it/wol/pc/r6/lp-i/202018322/1/0\"><strong>Ges&#xF9; compie il suo primo miracolo</strong></a><strong>&#x201D;: </strong>(10&#xA0;min)"
    }, 
    "__v" : NumberInt(0)
}
{ 
    "_id" : ObjectId("5b7a85856ba55a001459e76a"), 
    "congregation" : ObjectId("59ad334be52d8108cc2ca573"), 
    "date" : ISODate("2018-09-12T10:00:00.000+0000"), 
    "completed" : false, 
    "type" : {
        "withSupervisor" : true, 
        "disableSchool" : false, 
        "meeting" : true, 
        "label" : "Adunanza normale", 
        "id" : NumberInt(0)
    }, 
    "supervisor" : false, 
    "primarySchool" : true, 
    "secondarySchool" : true, 
    "initialPrayer" : null, 
    "finalPrayer" : null, 
    "president" : null, 
    "initialSong" : "  <a href=\"/it/wol/pc/r6/lp-i/202018324/0/0\">Cantico&#xA0;57</a> e preghiera", 
    "finalSong" : "  <a target=\"_blank\" href=\"https://wol.jw.org/it/wol/pc/r6/lp-i/202018324/10/0\">Cantico&#xA0;35</a> e preghiera", 
    "intervalSong" : "  <a target=\"_blank\" href=\"https://wol.jw.org/it/wol/pc/r6/lp-i/202018324/6/0\">Cantico&#xA0;77</a>", 
    "congregationBibleStudy" : {
        "brother" : null, 
        "label" : "  <strong>Studio biblico di congregazione: </strong>(30&#xA0;min) <a target=\"_blank\" href=\"https://wol.jw.org/it/wol/pc/r6/lp-i/202018324/8/0\"><em>jy </em>cap.&#xA0;35 parr.&#xA0;20-27</a> e riquadro &#x201C;<a target=\"_blank\" href=\"https://wol.jw.org/it/wol/pc/r6/lp-i/202018324/9/0\">L&#x2019;efficacia della ripetizione</a>&#x201D;", 
        "reader" : null
    }, 
    "christianLivingPart" : [
        {
            "label" : "  <strong>&#x201C;</strong><a target=\"_blank\" href=\"https://wol.jw.org/it/wol/pc/r6/lp-i/202018324/7/0\"><strong>Affiniamo le nostre capacit&#xE0; nel ministero | Iniziare conversazioni che permettono di dare testimonianza</strong></a><strong>&#x201D;: </strong>(15&#xA0;min) Trattazione. Concludi incoraggiando tutti a iniziare almeno una conversazione durante la settimana. Alla prossima adunanza infrasettimanale i proclamatori potranno raccontare le esperienze avute.", 
            "brother" : ObjectId("594bdb4e3545c51678fbad0b"), 
            "_id" : ObjectId("5b7a85856ba55a001459e76b")
        }
    ], 
    "bibleStudy" : {
        "label" : "  <strong>Discorso: </strong>(6&#xA0;min o meno) <a target=\"_blank\" href=\"https://wol.jw.org/it/wol/pc/r6/lp-i/202018324/5/0\"><em>wp16.2 </em>9-10 parr.&#xA0;1-4</a>. Tema: Spiegazione di <a target=\"_blank\" href=\"https://wol.jw.org/it/wol/bc/r6/lp-i/202018324/7/0\" data-bid=\"8-1\" class=\"b\">Giovanni 4:23</a>.", 
        "video" : false, 
        "secondarySchool" : {
            "gender" : "M", 
            "student" : null, 
            "isTalk" : true, 
            "assistant" : null, 
            "updated" : false, 
            "made" : NumberInt(0), 
            "pointCompleted" : false
        }, 
        "primarySchool" : {
            "gender" : "M", 
            "student" : null, 
            "isTalk" : true, 
            "assistant" : null, 
            "updated" : false, 
            "made" : NumberInt(0), 
            "pointCompleted" : false
        }
    }, 
    "returnVisit" : {
        "label" : "  <strong>Video della prima visita ulteriore: </strong>(5&#xA0;min) Mostra il <a target=\"_blank\" href=\"http://www.jw.org/finder?pub=mwbv&amp;issue=201809&amp;track=2\" data-video=\"webpubvid://?pub=mwbv&amp;issue=201809&amp;track=2\">video</a> e trattalo con l&#x2019;uditorio.", 
        "video" : true, 
        "secondarySchool" : {
            "gender" : "", 
            "student" : null, 
            "assistant" : null, 
            "updated" : false, 
            "made" : NumberInt(0), 
            "pointCompleted" : false
        }, 
        "primarySchool" : {
            "gender" : "", 
            "student" : null, 
            "assistant" : null, 
            "updated" : false, 
            "made" : NumberInt(0), 
            "pointCompleted" : false
        }
    }, 
    "initialCall" : {
        "label" : "  <strong>Primo contatto: </strong>(2&#xA0;min o meno) Usa la <a target=\"_blank\" class=\"it\" href=\"https://wol.jw.org/it/wol/tc/r6/lp-i/202018324/0\">conversazione modello</a>.", 
        "video" : false, 
        "secondarySchool" : {
            "gender" : "", 
            "student" : null, 
            "assistant" : null, 
            "updated" : false, 
            "made" : NumberInt(0), 
            "pointCompleted" : false
        }, 
        "primarySchool" : {
            "gender" : "", 
            "student" : null, 
            "assistant" : null, 
            "updated" : false, 
            "made" : NumberInt(0), 
            "pointCompleted" : false
        }
    }, 
    "bibleReading" : {
        "label" : "  <strong>Lettura biblica: </strong>(4&#xA0;min o meno) <a target=\"_blank\" href=\"https://wol.jw.org/it/wol/bc/r6/lp-i/202018324/6/0\" data-bid=\"7-1\" class=\"b\">Gv 4:1-15</a>", 
        "secondarySchool" : {
            "student" : null, 
            "updated" : false, 
            "made" : NumberInt(0), 
            "pointCompleted" : false
        }, 
        "primarySchool" : {
            "student" : null, 
            "updated" : false, 
            "made" : NumberInt(0), 
            "pointCompleted" : false
        }
    }, 
    "presentationExercise" : {
        "enabled" : false, 
        "brother" : null, 
        "label" : ""
    }, 
    "gems" : {
        "brother" : null, 
        "label" : "  <strong>Scaviamo per trovare gemme spirituali: </strong>(8&#xA0;min)"
    }, 
    "talk" : {
        "brother" : null, 
        "label" : "  <strong>&#x201C;</strong><a target=\"_blank\" href=\"https://wol.jw.org/it/wol/pc/r6/lp-i/202018324/1/0\"><strong>Ges&#xF9; d&#xE0; testimonianza a una samaritana</strong></a><strong>&#x201D;: </strong>(10&#xA0;min)"
    }, 
    "__v" : NumberInt(0)
}
{ 
    "_id" : ObjectId("5b7a85856ba55a001459e76f"), 
    "congregation" : ObjectId("59ad334be52d8108cc2ca573"), 
    "date" : ISODate("2018-09-26T10:00:00.000+0000"), 
    "completed" : false, 
    "type" : {
        "withSupervisor" : true, 
        "disableSchool" : false, 
        "meeting" : true, 
        "label" : "Adunanza normale", 
        "id" : NumberInt(0)
    }, 
    "supervisor" : false, 
    "primarySchool" : true, 
    "secondarySchool" : true, 
    "initialPrayer" : null, 
    "finalPrayer" : null, 
    "president" : null, 
    "initialSong" : "  <a href=\"/it/wol/pc/r6/lp-i/202018330/0/0\">Cantico&#xA0;12</a> e preghiera", 
    "finalSong" : "  <a target=\"_blank\" href=\"https://wol.jw.org/it/wol/pc/r6/lp-i/202018330/10/0\">Cantico 119</a> e preghiera", 
    "intervalSong" : "  <a target=\"_blank\" href=\"https://wol.jw.org/it/wol/pc/r6/lp-i/202018330/7/0\">Cantico&#xA0;103</a>", 
    "congregationBibleStudy" : {
        "brother" : null, 
        "label" : "  <strong>Studio biblico di congregazione: </strong>(30&#xA0;min) <a target=\"_blank\" href=\"https://wol.jw.org/it/wol/pc/r6/lp-i/202018330/9/0\"><em>jy </em>cap.&#xA0;36</a>", 
        "reader" : null
    }, 
    "christianLivingPart" : [
        {
            "label" : "  <strong>&#x201C;</strong><a target=\"_blank\" href=\"https://wol.jw.org/it/wol/pc/r6/lp-i/202018330/8/0\"><strong>Imitiamo l&#x2019;umilt&#xE0; e la modestia di Cristo</strong></a><strong>&#x201D;: </strong>(15&#xA0;min) Trattazione. Fai vedere i video.", 
            "brother" : ObjectId("594bdb043545c51678fbad09"), 
            "_id" : ObjectId("5b7a85856ba55a001459e770")
        }
    ], 
    "bibleStudy" : {
        "label" : "  <strong>Studio biblico: </strong>(6&#xA0;min o meno) <a target=\"_blank\" href=\"https://wol.jw.org/it/wol/pc/r6/lp-i/202018330/6/0\"><em>lv </em>9-10 parr.&#xA0;10-11</a>", 
        "video" : false, 
        "secondarySchool" : {
            "gender" : "", 
            "student" : null, 
            "isTalk" : false, 
            "assistant" : null, 
            "updated" : false, 
            "made" : NumberInt(0), 
            "pointCompleted" : false
        }, 
        "primarySchool" : {
            "gender" : "", 
            "student" : null, 
            "isTalk" : false, 
            "assistant" : null, 
            "updated" : false, 
            "made" : NumberInt(0), 
            "pointCompleted" : false
        }
    }, 
    "returnVisit" : {
        "label" : "  <strong>Terza visita ulteriore: </strong>(3&#xA0;min o meno) Scegli tu un passo biblico, e poi offri una pubblicazione di studio.", 
        "video" : false, 
        "secondarySchool" : {
            "gender" : "", 
            "student" : null, 
            "assistant" : null, 
            "updated" : false, 
            "made" : NumberInt(0), 
            "pointCompleted" : false
        }, 
        "primarySchool" : {
            "gender" : "", 
            "student" : null, 
            "assistant" : null, 
            "updated" : false, 
            "made" : NumberInt(0), 
            "pointCompleted" : false
        }
    }, 
    "initialCall" : {
        "label" : "  <strong>Seconda visita ulteriore: </strong>(3&#xA0;min o meno) Inizia con la <a target=\"_blank\" class=\"it\" href=\"https://wol.jw.org/it/wol/tc/r6/lp-i/202018330/0\">conversazione modello</a>. Poi invita la persona all&#x2019;adunanza.", 
        "video" : false, 
        "secondarySchool" : {
            "gender" : "", 
            "student" : null, 
            "assistant" : null, 
            "updated" : false, 
            "made" : NumberInt(0), 
            "pointCompleted" : false
        }, 
        "primarySchool" : {
            "gender" : "", 
            "student" : null, 
            "assistant" : null, 
            "updated" : false, 
            "made" : NumberInt(0), 
            "pointCompleted" : false
        }
    }, 
    "bibleReading" : {
        "label" : "  <strong>Lettura biblica: </strong>(4&#xA0;min o meno) <a target=\"_blank\" href=\"https://wol.jw.org/it/wol/bc/r6/lp-i/202018330/6/0\" data-bid=\"7-1\" class=\"b\">Gv 8:31-47</a>", 
        "secondarySchool" : {
            "student" : null, 
            "updated" : false, 
            "made" : NumberInt(0), 
            "pointCompleted" : false
        }, 
        "primarySchool" : {
            "student" : null, 
            "updated" : false, 
            "made" : NumberInt(0), 
            "pointCompleted" : false
        }
    }, 
    "presentationExercise" : {
        "enabled" : false, 
        "brother" : null, 
        "label" : ""
    }, 
    "gems" : {
        "brother" : null, 
        "label" : "  <strong>Scaviamo per trovare gemme spirituali: </strong>(8&#xA0;min)"
    }, 
    "talk" : {
        "brother" : null, 
        "label" : "  <strong>&#x201C;</strong><a target=\"_blank\" href=\"https://wol.jw.org/it/wol/pc/r6/lp-i/202018330/1/0\"><strong>Ges&#xF9; glorific&#xF2; suo Padre</strong></a><strong>&#x201D;: </strong>(10&#xA0;min)"
    }, 
    "__v" : NumberInt(0)
}
